setup.py
dj_distributions/Binomialdistribution.py
dj_distributions/Gaussiandistribution.py
dj_distributions/Generaldistribution.py
dj_distributions/__init__.py
dj_distributions.egg-info/PKG-INFO
dj_distributions.egg-info/SOURCES.txt
dj_distributions.egg-info/dependency_links.txt
dj_distributions.egg-info/not-zip-safe
dj_distributions.egg-info/top_level.txt